kaptcha/__init__.py
kaptcha/captcha.py
kaptcha/font1.ttf
kaptcha/font2.ttf
kaptcha/font3.ttf
kaptcha/font4.ttf
kaptcha-1.0.1.dist-info/LICENSE
kaptcha-1.0.1.dist-info/METADATA
kaptcha-1.0.1.dist-info/WHEEL
kaptcha-1.0.1.dist-info/top_level.txt
kaptcha-1.0.1.dist-info/RECORD
