Metadata-Version: 2.1
Name: kaptcha
Version: 1.0.1
Summary: 一个图形验证码生成工具
Home-page: https://github.com/antonvanke/kaptcha
Author: AntonVanke
Author-email: antonvanke@hotmail.com
License: MIT License
Keywords: Captcha Verification-Code Code
Platform: UNKNOWN
Classifier: Programming Language :: Python :: 3
Classifier: License :: OSI Approved :: MIT License
Classifier: Operating System :: OS Independent
Requires-Python: >3.7
License-File: LICENSE
Requires-Dist: pillow
